ramanbiolib/__init__.py
ramanbiolib/search.py
ramanbiolib/db/__init__.py
ramanbiolib/db/extraction.py
ramanbiolib/db/metadata_db.csv
ramanbiolib/db/raman_peaks_db.csv
ramanbiolib/db/raman_spectra_db.csv
ramanbiolib/tests/__init__.py
ramanbiolib/tests/test_search.py
ramanbiolib-1.0.0.post5.dist-info/LICENSE
ramanbiolib-1.0.0.post5.dist-info/LICENSE-ODbL
ramanbiolib-1.0.0.post5.dist-info/METADATA
ramanbiolib-1.0.0.post5.dist-info/WHEEL
ramanbiolib-1.0.0.post5.dist-info/top_level.txt
ramanbiolib-1.0.0.post5.dist-info/RECORD
