Metadata-Version: 2.1
Name: ramanbiolib
Version: 1.0.0.post5
Summary: Biomolecules identification search using Raman spectra.
Author: Marcelo Teran Miranda
License: GNU GPLv3
Project-URL: Homepage, https://github.com/mteranm/ramanbiolib
Project-URL: Repository, https://github.com/mteranm/ramanbiolib
Project-URL: API Docs, https://mteranm.github.io/ramanbiolib/
Project-URL: Bug Tracker, https://github.com/mteranm/ramanbiolib/issues
Keywords: raman,spectroscopy,biomolecules
Classifier: License :: OSI Approved :: GNU General Public License v3 (GPLv3)
Classifier: Programming Language :: Python :: 3
Requires-Python: <3.12,>=3.7
License-File: LICENSE
License-File: LICENSE-ODbL
Requires-Dist: numpy <1.23,>=1.21.6 ; python_version < "3.9"
Requires-Dist: scipy <1.10,>=1.7.3 ; python_version < "3.9"
Requires-Dist: pandas <1.5,>=1.1.5 ; python_version < "3.9"
Requires-Dist: plotly <6.0,>=5.0 ; python_version < "3.9"
Requires-Dist: numpy <1.25,>=1.21.6 ; python_version == "3.10"
Requires-Dist: scipy <1.11,>=1.7.3 ; python_version == "3.10"
Requires-Dist: pandas >=1.5 ; python_version == "3.10"
Requires-Dist: plotly <6.0,>=5.0 ; python_version == "3.10"
Requires-Dist: numpy <1.24,>=1.21.6 ; python_version == "3.9"
Requires-Dist: scipy <1.11,>=1.7.3 ; python_version == "3.9"
Requires-Dist: pandas <1.6,>=1.3 ; python_version == "3.9"
Requires-Dist: plotly <6.0,>=5.0 ; python_version == "3.9"
Requires-Dist: numpy >=1.24 ; python_version >= "3.11"
Requires-Dist: scipy >=1.10 ; python_version >= "3.11"
Requires-Dist: pandas >=1.5 ; python_version >= "3.11"
Requires-Dist: plotly <6.0,>=5.0 ; python_version >= "3.11"
Provides-Extra: extraction
Requires-Dist: opencv-python <4.11,>=4.10.0.84 ; extra == 'extraction'
